setup.py
sr_dsnd_probability/Binomialdistribution.py
sr_dsnd_probability/Gaussiandistribution.py
sr_dsnd_probability/Generaldistribution.py
sr_dsnd_probability/__init__.py
sr_dsnd_probability.egg-info/PKG-INFO
sr_dsnd_probability.egg-info/SOURCES.txt
sr_dsnd_probability.egg-info/dependency_links.txt
sr_dsnd_probability.egg-info/not-zip-safe
sr_dsnd_probability.egg-info/top_level.txt