Metadata-Version: 1.0
Name: sr-dsnd-probability
Version: 0.1
Summary: Gaussian and Binomial distributions
Home-page: UNKNOWN
Author: Sangeetha Ramamurthy
Author-email: sramamurthy@ucdavis.edu
License: UNKNOWN
Platform: UNKNOWN
